padepy/__init__.py
padepy/baker_algorithm.py
padepy/direct_algorithm.py
padepy/maclaurin.py
padepy-0.1.0.dist-info/LICENSE
padepy-0.1.0.dist-info/METADATA
padepy-0.1.0.dist-info/WHEEL
padepy-0.1.0.dist-info/top_level.txt
padepy-0.1.0.dist-info/RECORD
