Metadata-Version: 2.1
Name: padepy
Version: 0.1.0
Summary: Padé approximmants calculation.
Home-page: https://github.com/daSilvaRafael/padepy
Author: Rafael da Silva
Author-email: rafael6braga@gmail.com
Classifier: Programming Language :: Python :: 3
Classifier: License :: OSI Approved :: MIT License
Classifier: Operating System :: OS Independent
Requires-Python: >=3.7
License-File: LICENSE
